<annotation>
	<folder>images</folder>
	<filename>pigweed (1196).JPG</filename>
	<path>G:\my_datasets\images_annatations\3.pigweed\images\pigweed (1196).JPG</path>
	<source>
		<database>Unknown</database>
	</source>
	<size>
		<width>2992</width>
		<height>2000</height>
		<depth>3</depth>
	</size>
	<segmented>0</segmented>
	<object>
		<name>pigweed</name>
		<pose>Unspecified</pose>
		<truncated>0</truncated>
		<difficult>0</difficult>
		<bndbox>
			<xmin>936</xmin>
			<ymin>557</ymin>
			<xmax>2028</xmax>
			<ymax>1381</ymax>
		</bndbox>
	</object>
	<object>
		<name>pigweed</name>
		<pose>Unspecified</pose>
		<truncated>1</truncated>
		<difficult>0</difficult>
		<bndbox>
			<xmin>320</xmin>
			<ymin>1</ymin>
			<xmax>1276</xmax>
			<ymax>867</ymax>
		</bndbox>
	</object>
</annotation>
