<annotation>
	<folder>images</folder>
	<filename>pigweed (670).JPG</filename>
	<path>G:\my_datasets\images_annatations\3.pigweed\images\pigweed (670).JPG</path>
	<source>
		<database>Unknown</database>
	</source>
	<size>
		<width>2992</width>
		<height>2000</height>
		<depth>3</depth>
	</size>
	<segmented>0</segmented>
	<object>
		<name>pigweed</name>
		<pose>Unspecified</pose>
		<truncated>0</truncated>
		<difficult>0</difficult>
		<bndbox>
			<xmin>645</xmin>
			<ymin>582</ymin>
			<xmax>2211</xmax>
			<ymax>1653</ymax>
		</bndbox>
	</object>
	<object>
		<name>pigweed</name>
		<pose>Unspecified</pose>
		<truncated>1</truncated>
		<difficult>0</difficult>
		<bndbox>
			<xmin>454</xmin>
			<ymin>1</ymin>
			<xmax>1802</xmax>
			<ymax>708</ymax>
		</bndbox>
	</object>
</annotation>
