<annotation>
	<folder>images</folder>
	<filename>abutilon theophrasti (22).JPG</filename>
	<path>G:\my_datasets\images_annatations\6.tongma\images\abutilon theophrasti (22).JPG</path>
	<source>
		<database>Unknown</database>
	</source>
	<size>
		<width>2992</width>
		<height>2000</height>
		<depth>3</depth>
	</size>
	<segmented>0</segmented>
	<object>
		<name>abutilon theophrasti</name>
		<pose>Unspecified</pose>
		<truncated>0</truncated>
		<difficult>0</difficult>
		<bndbox>
			<xmin>785</xmin>
			<ymin>176</ymin>
			<xmax>1989</xmax>
			<ymax>1653</ymax>
		</bndbox>
	</object>
</annotation>
