<annotation>
	<folder>images</folder>
	<filename>cocklebur (91).JPG</filename>
	<path>G:\my_datasets\images_annatations\1.cocklebur\images\cocklebur (91).JPG</path>
	<source>
		<database>Unknown</database>
	</source>
	<size>
		<width>2992</width>
		<height>2000</height>
		<depth>3</depth>
	</size>
	<segmented>0</segmented>
	<object>
		<name>cocklebur</name>
		<pose>Unspecified</pose>
		<truncated>0</truncated>
		<difficult>0</difficult>
		<bndbox>
			<xmin>378</xmin>
			<ymin>113</ymin>
			<xmax>2546</xmax>
			<ymax>1922</ymax>
		</bndbox>
	</object>
</annotation>
