<annotation>
	<folder>images</folder>
	<filename>horseweed (147).jpg</filename>
	<path>G:\my_datasets\images_annatations\24.horseweed\images\horseweed (147).jpg</path>
	<source>
		<database>Unknown</database>
	</source>
	<size>
		<width>2976</width>
		<height>3968</height>
		<depth>3</depth>
	</size>
	<segmented>0</segmented>
	<object>
		<name>horseweed</name>
		<pose>Unspecified</pose>
		<truncated>0</truncated>
		<difficult>0</difficult>
		<bndbox>
			<xmin>644</xmin>
			<ymin>1036</ymin>
			<xmax>1897</xmax>
			<ymax>2453</ymax>
		</bndbox>
	</object>
</annotation>
