<annotation>
	<folder>images</folder>
	<filename>Black nightshade (250).JPG</filename>
	<path>G:\my_datasets\images_annatations\19.Black nightshade\images\Black nightshade (250).JPG</path>
	<source>
		<database>Unknown</database>
	</source>
	<size>
		<width>2992</width>
		<height>2000</height>
		<depth>3</depth>
	</size>
	<segmented>0</segmented>
	<object>
		<name>Black_nightshade</name>
		<pose>Unspecified</pose>
		<truncated>0</truncated>
		<difficult>0</difficult>
		<bndbox>
			<xmin>784</xmin>
			<ymin>242</ymin>
			<xmax>2020</xmax>
			<ymax>1800</ymax>
		</bndbox>
	</object>
	<object>
		<name>Black_nightshade</name>
		<pose>Unspecified</pose>
		<truncated>0</truncated>
		<difficult>0</difficult>
		<bndbox>
			<xmin>41</xmin>
			<ymin>1340</ymin>
			<xmax>707</xmax>
			<ymax>1936</ymax>
		</bndbox>
	</object>
</annotation>
