<annotation>
	<folder>images</folder>
	<filename>purslane (400).JPG</filename>
	<path>G:\my_datasets\images_annations\2.purslane\images\purslane (400).JPG</path>
	<source>
		<database>Unknown</database>
	</source>
	<size>
		<width>2992</width>
		<height>2000</height>
		<depth>3</depth>
	</size>
	<segmented>0</segmented>
	<object>
		<name>purslane</name>
		<pose>Unspecified</pose>
		<truncated>0</truncated>
		<difficult>0</difficult>
		<bndbox>
			<xmin>395</xmin>
			<ymin>736</ymin>
			<xmax>1921</xmax>
			<ymax>1996</ymax>
		</bndbox>
	</object>
	<object>
		<name>purslane</name>
		<pose>Unspecified</pose>
		<truncated>0</truncated>
		<difficult>0</difficult>
		<bndbox>
			<xmin>1167</xmin>
			<ymin>31</ymin>
			<xmax>2578</xmax>
			<ymax>1048</ymax>
		</bndbox>
	</object>
</annotation>
