<annotation>
	<folder>images</folder>
	<filename>purslane (646).jpg</filename>
	<path>G:\my_datasets\images_annations\2.purslane\images\purslane (646).jpg</path>
	<source>
		<database>Unknown</database>
	</source>
	<size>
		<width>2976</width>
		<height>3968</height>
		<depth>3</depth>
	</size>
	<segmented>0</segmented>
	<object>
		<name>purslane</name>
		<pose>Unspecified</pose>
		<truncated>0</truncated>
		<difficult>0</difficult>
		<bndbox>
			<xmin>425</xmin>
			<ymin>2062</ymin>
			<xmax>1672</xmax>
			<ymax>2867</ymax>
		</bndbox>
	</object>
	<object>
		<name>purslane</name>
		<pose>Unspecified</pose>
		<truncated>0</truncated>
		<difficult>0</difficult>
		<bndbox>
			<xmin>1272</xmin>
			<ymin>1388</ymin>
			<xmax>2172</xmax>
			<ymax>2215</ymax>
		</bndbox>
	</object>
</annotation>
